miniacd-0.1.3.dist-info/METADATA
miniacd-0.1.3.dist-info/WHEEL
miniacd-0.1.3.dist-info/entry_points.txt
miniacd-0.1.3.dist-info/licenses/LICENSE-APACHE
miniacd-0.1.3.dist-info/licenses/LICENSE-MIT
miniacd/__init__.py
miniacd/cli.py
miniacd/miniacd.abi3.so
miniacd-0.1.3.dist-info/RECORD
