Metadata-Version: 2.4
Name: miniacd
Version: 0.1.3
Classifier: Topic :: Scientific/Engineering
Requires-Dist: click>=8.0.0
Requires-Dist: trimesh>=4.0.0
License-File: LICENSE-APACHE
License-File: LICENSE-MIT
Summary: Approximate convex decomposition of 3D meshes
Author: Kyle Cesare
Author-email: kcesare@gmail.com
License-Expression: MIT OR Apache-2.0
Requires-Python: >=3.9
Project-URL: homepage, https://github.com/kylc/miniacd
